sirfck.cpython-39-x86_64-linux-gnu.so
two/__init__.py
two/core.py
two/twoso.py
two/vb.py
two_electron-1.1.1.dist-info/METADATA
two_electron-1.1.1.dist-info/WHEEL
two_electron-1.1.1.dist-info/top_level.txt
two_electron-1.1.1.dist-info/RECORD
